pytagged/__init__.py
pytagged/_files_utils.py
pytagged/_mode.py
pytagged/_utils.py
pytagged/app.py
pytagged/cli.py
pytagged/nline.py
pytagged/options.py
pytagged-0.2.0.dist-info/LICENSE
pytagged-0.2.0.dist-info/METADATA
pytagged-0.2.0.dist-info/WHEEL
pytagged-0.2.0.dist-info/entry_points.txt
pytagged-0.2.0.dist-info/top_level.txt
pytagged-0.2.0.dist-info/RECORD
