Metadata-Version: 2.1
Name: pytagged
Version: 0.2.0
Summary: Auto comment cli
Home-page: https://github.com/ntn9995/pytagged
Author: 1Karus
Maintainer: 1Karus
License: MIT
Keywords: cli,console
Platform: UNKNOWN
Classifier: Environment :: Console
Classifier: Intended Audience :: Developers
Classifier: Operating System :: OS Independent
Classifier: Programming Language :: Python :: 3.6
Classifier: Programming Language :: Python :: 3.7
Classifier: Programming Language :: Python :: 3.8
Classifier: Programming Language :: Python :: Implementation :: CPython
Requires-Python: >=3.6
